setup.py
i18n/__init__.py
i18n/__main__.py
i18n/cmdline.py
i18n/dbtranslator.py
i18n/translator.py
i18n.egg-info/PKG-INFO
i18n.egg-info/SOURCES.txt
i18n.egg-info/dependency_links.txt
i18n.egg-info/requires.txt
i18n.egg-info/top_level.txt