Metadata-Version: 1.0
Name: i18n
Version: 0.1
Summary: Simplify the development of internationalized applications
Home-page: http://bitbucket.org/antocuni/i18n
Author: Antonio Cuni
Author-email: anto.cuni@gmail.com
License: BSD
Keywords: i18n gettext pybabel translation
Platform: UNKNOWN
Classifier: Development Status :: 4 - Beta
Classifier: License :: OSI Approved :: BSD License
Classifier: Programming Language :: Python
Classifier: Intended Audience :: Developers
Classifier: Operating System :: OS Independent
Classifier: Topic :: Software Development :: Internationalization
